gempaterkini/__init__.py
Latestearthquake_Indonesia_byTaufik-0.1.dist-info/LICENSE
Latestearthquake_Indonesia_byTaufik-0.1.dist-info/METADATA
Latestearthquake_Indonesia_byTaufik-0.1.dist-info/WHEEL
Latestearthquake_Indonesia_byTaufik-0.1.dist-info/top_level.txt
Latestearthquake_Indonesia_byTaufik-0.1.dist-info/RECORD
